latexminted/__init__.py
latexminted/cmdline.py
latexminted/command_batch.py
latexminted/command_clean.py
latexminted/command_config.py
latexminted/command_highlight.py
latexminted/command_styledef.py
latexminted/debug.py
latexminted/err.py
latexminted/fmtversion.py
latexminted/load_data.py
latexminted/messages.py
latexminted/version.py
latexminted/restricted/__init__.py
latexminted/restricted/_latexminted_config.py
latexminted/restricted/_load_custom_lexer.py
latexminted/restricted/_restricted_pathlib.py
latexminted-0.6.0.dist-info/licenses/CHANGELOG_LATEXMINTED_PYTHON_PACKAGE.md
latexminted-0.6.0.dist-info/licenses/LICENSE.txt
latexminted-0.6.0.dist-info/licenses/RESTRICTED_SHELL_ESCAPE.md
latexminted-0.6.0.dist-info/licenses/latexminted.1
latexminted-0.6.0.dist-info/METADATA
latexminted-0.6.0.dist-info/WHEEL
latexminted-0.6.0.dist-info/entry_points.txt
latexminted-0.6.0.dist-info/top_level.txt
latexminted-0.6.0.dist-info/RECORD
