Metadata-Version: 2.4
Name: latexminted
Version: 0.6.0
Summary: Python library for LaTeX minted package
Author-email: "Geoffrey M. Poore" <gpoore@gmail.com>
License: latexminted Python package
Project-URL: homepage, https://github.com/gpoore/minted/tree/main/python/
Project-URL: repository, https://github.com/gpoore/minted
Project-URL: changelog, https://github.com/gpoore/minted/blob/main/python/CHANGELOG_LATEXMINTED_PYTHON_PACKAGE.md
Keywords: LaTeX,syntax highlighting,Pygments
Classifier: Development Status :: 4 - Beta
Classifier: Programming Language :: Python
Classifier: Environment :: Console
Classifier: Intended Audience :: Developers
Classifier: Intended Audience :: Education
Classifier: Intended Audience :: Science/Research
Classifier: License :: OSI Approved
Classifier: Operating System :: OS Independent
Classifier: Topic :: Text Processing :: Markup :: LaTeX
Requires-Python: >=3.8
License-File: LICENSE.txt
License-File: CHANGELOG_LATEXMINTED_PYTHON_PACKAGE.md
License-File: RESTRICTED_SHELL_ESCAPE.md
License-File: latexminted.1
Requires-Dist: latex2pydata>=0.5.0
Requires-Dist: latexrestricted>=0.6.2
Requires-Dist: pygments>=2.17.0
Dynamic: license-file
